{"count":1281,"keys":{"MLUserverifyGalaxy(java.lang.String)V":"bh","MLjava.lang.Stringtrim(":"sS","Ljavax.accessibility.AccessibleContext":"cr","MLjavax.swing.JComponentsetActionMap(javax.swing.ActionMap)V":"d;","MLjava.awt.ComponentprocessEvent(java.awt.AWTEvent)V":"oc","MLjavax.swing.JComponentgetObscuredState(int)Vint)Vint)Vint)Vint)V":"fN","MLjava.awt.ComponentsetLocation(int)Vint)V":"lH","FUsermatches":"bE","Fjava.awt.ComponentCENTER_ALIGNMENT":"rx","MLjava.io.PrintStreamprintln(java.lang.String)V":"sa","Ljava.io.OutputStreamWriter":"sJ","Ljava.lang.Object":"u","FPlacename":"T","Fjava.awt.ComponentnameExplicitlySet":"qL","MLjava.awt.ComponentgetSize(":"lK","Fjava.awt.ComponentmouseMotionListenerK":"rj","Ljava.awt.Frame":"t7","MLjava.awt.ContainerpostsOldMouseEvents(":"jo","Ljavax.swing.event.EventListenerList":"gi","MLjava.awt.ComponentreadObject(java.io.ObjectInputStream)V":"pI","Fjavax.swing.JComponentpopupMenu":"gA","MLjavax.swing.JComponentfirePropertyChange(java.lang.String)Vint)Vint)V":"fi","Ljava.awt.GraphicsConfiguration":"hO","Fjavax.swing.JComponentRESERVED_6":"gU","MLjava.awt.ComponentinvalidateParent(":"mo","MLjava.io.IOExceptionprintStackTrace(":"sv","Fjava.awt.ContainerlayoutMgr":"j1","MLjava.awt.ContainerisFocusTraversalPolicySet(":"jg","MLjava.awt.ComponenteventEnabled(java.awt.AWTEvent)V":"nl","Ljavax.accessibility.Accessible":"ca","Ljava.awt.Dimension":"dr","Fjavax.swing.JComponentWHEN_ANCESTOR_OF_FOCUSED_COMPONENT":"gt","MLjava.lang.Stringsubstring(int)V":"s8","MLjava.awt.Containeradd(java.awt.Component)Vjava.lang.Object)Vint)V":"hL","MLjava.awt.ComponentsetCursor(java.awt.Cursor)V":"mv","MLjavax.swing.JPanelsetLayout(java.awt.LayoutManager)V":"tH","Fjavax.swing.JComponentmanagingFocusBackwardTraversalKeys":"f8","Ljavax.swing.TransferHandler.DropLocation":"eM","MLjava.awt.ComponentaddHierarchyBoundsListener(java.awt.event.HierarchyBoundsListener)V":"nA","MLjava.lang.Objectwait(long)Vint)V":"I","Pex-Pjava.awt.im":"n4","Ljavax.swing.InputMap":"d7","MLUserOperationsGetPasswordHash(java.lang.String)V":"bN","MLjava.awt.Componentrevalidate(":"mq","MLjava.io.PrintWriterclose(":"sV","Fjavax.swing.JComponentANCESTOR_INPUTMAP_CREATED":"gH","MLjava.awt.ContainergetHeavyweightContainer(":"hB","MLUserrejectUser(User)V":"bs","MLjava.awt.ComponentprocessKeyEvent(java.awt.event.KeyEvent)V":"oh","MLjavax.swing.JComponentsetNextFocusableComponent(java.awt.Component)V":"dc","MLjava.awt.ContainerreparentChild(java.awt.Component)V":"hH","MLjava.awt.ComponentgetComponentAt(java.awt.Point)V":"nd","MLjava.awt.ComponentrequestFocus(":"oQ","MLjava.awt.ComponentisMaximumSizeSet(":"me","Ljava.awt.Image":"mQ","MLjava.awt.ComponentpostEvent(java.awt.Event)V":"nn","Fjavax.swing.JComponentCOMPLETELY_OBSCURED":"f.","MLjava.awt.ComponentfirePropertyChange(java.lang.String)Vshort)Vshort)V":"pC","MLjava.awt.ComponentcreateHierarchyEvents(int)Vjava.awt.Component)Vjava.awt.Container)Vlong)Vboolean)V":"nF","MLjavax.swing.JComponentremoveAncestorListener(javax.swing.event.AncestorListener)V":"fw","MLjavax.swing.JComponentcompWriteObjectNotify(":"fX","MLjava.awt.ContaineradjustListeningChildren(long)Vint)V":"hU","MLjava.awt.ComponentinitializeFocusTraversalKeys(":"kA","MLjava.awt.Componentrepaint(":"mG","MLjavax.swing.JComponentfetchRectangle(":"cG","MLjavax.swing.JComponentrepaint(java.awt.Rectangle)V":"fC","Fjava.awt.Containerprinting":"j9","Ljavax.swing.JComponent.ReadObjectCallback":"f6","MLjava.awt.ContainergetListenersCount(int)Vboolean)V":"hY","P":"j","MLjava.awt.ComponentsetIgnoreRepaint(boolean)V":"m8","MLjava.awt.ComponentisVisible_NoClientCode(":"k2","MLjava.awt.ComponentisRecursivelyVisible(":"k3","Pex-Psun.awt":"hf","Pex-Pjava.util.concurrent.atomic":"g3","MLjava.awt.ContainertransferFocusDownCycle(":"jl","Fjavax.swing.JComponentautoscrolls":"gm","MLjava.io.BufferedReaderBufferedReader(java.io.Reader)V":"sn","Fjavax.swing.JComponentWHEN_IN_FOCUSED_WINDOW":"gu","MLjava.awt.ComponentsetLocale(java.util.Locale)V":"lz","MLjavax.swing.JPanelgetAccessibleContext(":"cq","MLjava.awt.ContainerrecursiveShowHeavyweightChildren(":"jM","MLjava.awt.ComponentsetComponentOrientation(java.awt.ComponentOrientation)V":"pJ","MLUserUser(":"Y","Fjava.awt.ComponentisFocusTraversableOverridden":"qQ","Fjava.awt.Componentvalid":"qG","Ljava.beans.VetoableChangeSupport":"gl","MLjava.awt.ComponentgetBackground(":"lr","MLjavax.swing.JComponentcheckIfChildObscuredBySibling(":"fO","MLjava.awt.ContainerrecursiveSubtractAndApplyShape(sun.java2d.pipe.Region)Vint)V":"jH","MLjavax.swing.JPanelgetUIClassID(":"cl","MLUserOperationsChangeStatus(int)V":"bM","MLjava.awt.ComponentapplyCompoundShape(sun.java2d.pipe.Region)V":"pY","MLjava.awt.ContainercountComponents(":"hk","Fjavax.swing.JComponentWHEN_FOCUSED":"gs","MLjava.awt.ContainerfindComponentAt(int)Vint)Vboolean)V":"iR","MLjava.awt.ContainercanContainFocusOwner(java.awt.Component)V":"hy","MLjava.awt.ContainergetMinimumSize(":"id","MLUsersetLastName(java.lang.String)V":"2","Pex-Pjavax.swing.border":"dz","Fjava.awt.ComponentFOCUS_TRAVERSABLE_DEFAULT":"qO","MLjavax.swing.JComponentisValidateRoot(":"fE","MLjavax.swing.JTextAreasetText(java.lang.String)V":"tD","MLjava.awt.ComponentinvalidateIfValid(":"mp","MLjava.lang.IntegerparseInt(java.lang.String)V":"sz","Fjava.awt.ContainerEMPTY_ARRAY":"jZ","Ljavax.swing.KeyStroke":"cE","MLjavax.swing.JComponentscrollRectToVisible(java.awt.Rectangle)V":"eF","Ljava.awt.event.ComponentEvent":"oe","Fjava.awt.Componentcursor":"qz","MLjavax.swing.JComponentdndDone(":"eO","MLjava.awt.Containeradd(java.awt.Component)V":"hr","MLjava.awt.ContainerinitializeFocusTraversalKeys(":"hi","MLjava.awt.ComponentcanBeFocusOwnerRecursively(":"pN","Ljava.awt.event.ContainerListener":"is","MLjava.awt.ComponentdoLayout(":"mk","Ljava.awt.event.ComponentListener":"np","Fjavax.swing.JComponentaaHint":"hc","MLjava.lang.Objectfinalize(":"J","MLjava.awt.ComponentgetBoundsOp(":"ky","LPicture":"n","Fjava.awt.Componentx":"qr","MLjava.awt.Componentbounds(":"lR","Fjava.awt.Componenty":"qs","MLUserOperationsRemoveUser(java.lang.String)V":"bK","MLjavax.swing.JComponentsetAlignmentX(float)V":"dI","Ljava.awt.Graphics":"cx","Fjava.awt.Containerlog":"jV","Fjava.awt.ComponentwindowListenerK":"rn","Ljava.util.Random":"sg","MLjavax.swing.JTextAreasetBackground(java.awt.Color)V":"tx","MLjava.awt.ComponentprocessComponentEvent(java.awt.event.ComponentEvent)V":"od","Fjavax.swing.JComponentCREATED_DOUBLE_BUFFER":"gK","MLjava.awt.ComponentisMixingNeeded(":"qg","Ljava.lang.CharSequence":"sM","Lsun.util.logging.PlatformLogger":"jX","MLjavax.swing.GroupLayoutsetHorizontalGroup(javax.swing.GroupLayout.Group)V":"tI","MLUsergetLastName(":"3","Ljava.lang.Comparable":"X","MLjava.awt.ContainergetBottommostComponentIndex(":"jC","MLjava.awt.BorderLayoutBorderLayout(":"t4","MLjavax.swing.GroupLayout.SequentialGroupaddComponent(java.awt.Component)Vint)Vint)Vint)V":"tY","MLjava.awt.ContainergetTraversalRoot(":"jc","MLUserOperationsChangeBio(java.lang.String)V":"bL","Ljava.awt.event.ActionListener":"dT","MLjava.util.ScannernextLine(":"sf","Ljava.io.PrintWriter":"i4","MLjavax.swing.JComponentreshape(int)Vint)Vint)Vint)V":"e5","Fjava.awt.ComponentcomponentSerializedDataVersion":"rT","MLUsergetFirstName(":"1","MLjava.awt.ComponentprocessHierarchyBoundsEvent(java.awt.event.HierarchyEvent)V":"oq","MLjava.awt.ContainerprintComponents(java.awt.Graphics)V":"io","MLjava.awt.ContainergetAccessibleChild(int)V":"jy","Ljavax.swing.JPanel":"bR","MLjava.awt.ComponentaddPropertyChangeListener(java.lang.String)Vjava.beans.PropertyChangeListener)V":"pu","Ljavax.swing.TransferHandler.HasGetTransferHandler":"cv","MLjava.awt.ComponentpaintHeavyweightComponents(java.awt.Graphics)V":"mF","MLjava.awt.ComponentgetSize(java.awt.Dimension)V":"l3","Fjava.awt.image.ImageObserverABORT":"r3","Fjavax.swing.JComponentRESERVED_2":"gQ","Fjavax.swing.JComponentRESERVED_3":"gR","MLjava.awt.ComponentisOpaque(":"l5","Fjavax.swing.JComponentRESERVED_4":"gS","Fjavax.swing.JComponentRESERVED_5":"gT","MLjava.awt.ContainerremoveNotify(":"iW","MLjava.awt.ContainergetTopmostComponentIndex(":"jB","MLSearchFunctionListUserFilters(":"V","Fjavax.swing.JComponentRESERVED_1":"gP","MLjavax.swing.JComponentgetComponentPopupMenu(":"cN","Fjavax.swing.JComponentPARTIALLY_OBSCURED":"f;","MLjava.awt.ComponentinitIDs(":"pR","Fjavax.swing.JComponentKEYBOARD_BINDINGS_KEY":"gw","MLjava.io.FileNotFoundExceptionprintStackTrace(":"sZ","MLjavax.swing.JComponentgetBounds(java.awt.Rectangle)V":"e6","MLjavax.swing.JComponentsuperProcessMouseMotionEvent(java.awt.event.MouseEvent)V":"eR","Fjava.awt.ComponentbackgroundEraseDisabled":"rK","MLjavax.swing.GroupLayout.SequentialGroupaddGroup(javax.swing.GroupLayout.Group)V":"tQ","Fjavax.swing.JComponentUNDEFINED_CONDITION":"gv","MLjava.lang.StringgetBytes(":"s4","MLUsergetProfile(":"bg","MLjava.awt.ContaineraddContainerListener(java.awt.event.ContainerListener)V":"ir","MLjava.awt.ContainerrecursiveRelocateHeavyweightChildren(java.awt.Point)V":"jO","MLjava.awt.ComponentadjustListeningChildrenOnParent(long)Vint)V":"nH","MLjava.awt.ComponentrelocateComponent(":"pO","MLjava.awt.ContainergetMaximumSize(":"if","MLjava.awt.ComponentdispatchMouseWheelToAncestor(java.awt.event.MouseWheelEvent)V":"nj","MLjava.awt.ContainerinitIDs(":"hh","MLjava.awt.ComponentsetBounds(java.awt.Rectangle)V":"lX","FViewProfilejPanel1":"b3","Fjava.awt.image.ImageObserverERROR":"r2","MLjava.awt.ContainergetComponentAt(int)Vint)V":"iL","MLjava.awt.ComponentgetName(":"kC","Pex-__defaultpackage$1":"bd","MLjavax.swing.JPanelgetUI(":"ch","MLjava.awt.ComponentprepareImage(java.awt.Image)Vint)Vint)Vjava.awt.image.ImageObserver)V":"mZ","MLjava.awt.ComponentgetFocusTraversalKeys_NoIDCheck(int)V":"oM","Fjavax.swing.JComponentOPAQUE_SET":"gY","MLCreateNewUsercreate(java.lang.String)Vjava.lang.String)Vjava.lang.String)Vjava.lang.String)V":"w","Fjava.awt.Componentparent":"qp","MLjava.awt.ComponentgetSiblingIndexAbove(":"p3","MLjava.awt.ComponentgetInsets_NoClientCode(":"mO","byte":"f","Fjavax.swing.JComponentlcdRenderingHint":"hd","MLjava.awt.Componentmove(int)Vint)V":"lI","MLjava.awt.Componentsize(":"lL","MLjava.awt.ColorColor(int)Vint)Vint)V":"th","Fjavax.swing.JComponentui":"gg","MLjava.awt.ComponentcheckCoalescing(":"n;","MLjava.security.MessageDigestdigest(byte[])V":"s3","MLjava.awt.ComponentgetAccessibleContext(":"pS","MLjava.io.FileReaderFileReader(java.lang.String)V":"sq","MLjavax.swing.JComponentsetTransferHandler(javax.swing.TransferHandler)V":"eI","MLjavax.swing.JComponentgetConditionForKeyStroke(javax.swing.KeyStroke)V":"d3","MLjava.awt.ContainergetFocusTraversalKeys(int)V":"i6","Ljava.io.PrintStream":"i2","MLjavax.swing.JPanelJPanel(java.awt.LayoutManager)Vboolean)V":"cb","MLjava.awt.ContainergetComponentsSync(":"ho","Ljava.lang.System":"sb","Ljava.io.Reader":"so","MLjava.awt.ComponentisCoalesceEventsOverriden(java.lang.Class<?>)V":"n.","MLjava.awt.ComponentgetAlignmentX(":"mg","Fjava.awt.ComponentfocusTraversalKeys":"qR","Fjavax.swing.JComponentACTIONMAP_CREATED":"gJ","MLjavax.swing.JComponentsetWriteObjCounter(javax.swing.JComponent)Vbyte)V":"fR","MLViewProfileinitComponents(User)V":"bT","MLjavax.swing.JComponentgetBaselineResizeBehavior(":"ee","FViewProfilejTextArea1":"b6","MLjavax.swing.GroupLayout.SequentialGroupaddComponent(java.awt.Component)V":"t1","MLjavax.swing.JLabelJLabel(":"tb","MLjava.awt.ComponentmouseExit(java.awt.Event)Vint)Vint)V":"ox","LSearchFunction":"p","MLjavax.swing.JComponentpaintBorder(java.awt.Graphics)V":"cX","MLjava.awt.ComponentgetCursor(":"my","MLjava.awt.ContainersetFocusTraversalPolicyProvider(boolean)V":"jj","Ljava.lang.Short":"tW","Fjava.awt.image.ImageObserverALLBITS":"r1","Fjavax.swing.JComponentWIF_INPUTMAP_CREATED":"gI","LCreateNewUser":"k","Fjava.awt.ComponentactionListenerK":"rb","MLjavax.swing.GroupLayout.ParallelGroupaddGroup(javax.swing.GroupLayout.Group)V":"tL","MLjavax.swing.JComponentprocessMouseMotionEvent(java.awt.event.MouseEvent)V":"eQ","MLjavax.swing.JComponentgetToolTipText(":"ex","Fjava.awt.ContainerfocusTraversalPolicy":"j4","MLjava.awt.ComponentgetAlignmentY(":"mh","MLjavax.swing.JComponentgetVetoableChangeListeners(":"fp","Ljavax.swing.JRootPane":"fW","MLjavax.swing.JComponentgetInsets(":"dC","MLjava.awt.ComponentfirePropertyChange(java.lang.String)Vint)Vint)V":"pz","Fjavax.swing.JComponentreadObjectCallbacks":"f4","MLjavax.swing.JComponentwriteObject(java.io.ObjectOutputStream)V":"f0","MLjava.awt.ComponentgetHeight(":"l1","MLjava.awt.ComponentprocessMouseMotionEvent(java.awt.event.MouseEvent)V":"oj","MLjava.awt.ComponentgetNextFocusCandidate(":"o9","MLjava.awt.ComponentgetSiblingIndexBelow(":"p6","MLjavax.swing.JComponentgetRootPane(":"fV","Pex-Pjava.util":"bp","MLjava.awt.ContainergetAccessibleChildrenCount(":"jx","Ljava.lang.Class":"z","MLjavax.swing.JComponentgetY(":"e;","MLjava.awt.ContainersetFocusTraversalPolicy(java.awt.FocusTraversalPolicy)V":"jd","MLjavax.swing.JLabelsetIcon(javax.swing.Icon)V":"tq","MLjava.awt.Componentenable(":"lc","Ljava.awt.event.InputMethodListener":"nZ","MLjava.awt.ContainerisAncestorOf(java.awt.Component)V":"iX","Fjava.awt.ComponentfocusListenerK":"rf","MLPlacePlace(java.lang.String)V":"R","MLjava.awt.ComponentgetMouseMotionListeners(":"nT","MLjava.awt.ContainergetContainerListeners(":"iu","MLjavax.swing.JComponentgetRegisteredKeyStrokes(":"d2","Ljavax.swing.LayoutStyle.ComponentPlacement":"t0","Ljavax.swing.plaf.PanelUI":"cj","MLjavax.swing.JComponentunregisterKeyboardAction(javax.swing.KeyStroke)V":"d1","MLjava.awt.Containerprint(java.awt.Graphics)V":"ik","MLjava.awt.ComponentisCoalescingEnabled(":"oa","MLjava.awt.ComponentsetFocusTraversalKeys_NoIDCheck(int)Vjava.util.Set<? extends java.awt.AWTKeyStroke>)V":"oL","MLjavax.swing.JComponentgetX(":"e9","Ljava.awt.BufferCapabilities":"m4","Fjavax.swing.JComponentTOOL_TIP_TEXT_KEY":"gy","MLjava.awt.Componentaction(java.awt.Event)Vjava.lang.Object)V":"oA","MLjava.awt.ComponentsubtractAndApplyShapeBelowMe(":"qa","Fjava.awt.ComponentisAddNotifyComplete":"rJ","MLjavax.swing.JComponentprocessComponentKeyEvent(java.awt.event.KeyEvent)V":"eq","Fjavax.swing.JComponentFOCUS_TRAVERSAL_KEYS_FORWARD_SET":"g0","LTempArgsE":"be","void":"a","Fjava.awt.ComponentLEFT_ALIGNMENT":"rz","MLjavax.swing.JComponentparamString(":"f1","MLjava.awt.ComponentnotifyNewBounds(boolean)Vboolean)V":"lW","Fjavax.swing.JComponentNEXT_FOCUS":"gz","MLjava.awt.ComponentsetFont(java.awt.Font)V":"lw","MLjava.lang.Objectwait(":"G","MLjava.awt.ComponentgetColorModel(":"lA","Ljava.awt.image.ColorModel":"lB","MLjava.awt.ContainerremoveDelicately(java.awt.Component)Vjava.awt.Container)Vint)V":"hx","Fjava.awt.ComponentRIGHT_ALIGNMENT":"rA","Ljavax.swing.border.Border":"dA","MLjava.awt.ComponentisFocusTraversable(":"oF","MLjava.awt.ContainerareFocusTraversalKeysSet(int)V":"i7","LTempArgsT":"bG","Ljava.io.ObjectOutputStream":"co","Fjava.awt.ComponentboundsOp":"rG","MLjavax.swing.JComponentsetToolTipText(java.lang.String)V":"ew","MLjavax.swing.TransferHandler.HasGetTransferHandlergetTransferHandler(":"r7","MLjava.awt.ContainerpaintComponents(java.awt.Graphics)V":"il","MLjavax.swing.JComponentsetInputVerifier(javax.swing.InputVerifier)V":"dK","MLjava.awt.Componentlayout(":"ml","Fjava.awt.ComponentaccessibleContext":"rU","MLjavax.swing.JComponentsetUIProperty(java.lang.String)Vjava.lang.Object)V":"e1","MLjavax.swing.GroupLayout.ParallelGroupaddComponent(java.awt.Component)V":"tV","MLjava.awt.ComponentmouseDown(java.awt.Event)Vint)Vint)V":"os","Fjava.awt.ComponentcomponentOrientation":"q2","Fjavax.swing.JComponentancestorInputMap":"g8","Ljava.awt.event.MouseWheelListener":"nV","MLjava.awt.Componentdisable(":"le","MLjavax.swing.JComponentsetForeground(java.awt.Color)V":"ej","MLjavax.swing.JComponentisComponentObtainingGraphicsFrom(java.awt.Component)V":"cB","MLjava.awt.ComponentisShowing(":"k;","MLjava.awt.ComponentremoveFocusListener(java.awt.event.FocusListener)V":"nu","MLjavax.swing.JComponentfireVetoableChange(java.lang.String)Vjava.lang.Object)Vjava.lang.Object)V":"fk","MLjava.awt.ComponentgetComponentListeners(":"nr","MLjava.awt.ComponentcountHierarchyMembers(":"nE","Fjava.awt.ComponentownedWindowK":"rm","MLjava.lang.IntegertoString(int)Vint)V":"s9","Pex-Pjava.awt":"cc","Fjava.awt.ComponentminSize":"qW","MLjavax.swing.JComponentgetBaseline(int)Vint)V":"ed","MLjava.awt.ContainermixOnValidating(":"jU","Fjavax.swing.JComponenttempRectangles":"g5","MLjava.awt.ComponentgotFocus(java.awt.Event)Vjava.lang.Object)V":"oD","MLjava.awt.ComponentgetY(":"lZ","Ljavax.swing.InputVerifier":"dL","MLjavax.swing.ImageIconImageIcon(java.net.URL)V":"tt","Ljavax.swing.GroupLayout":"tF","MLjava.awt.ComponentgetAppliedShape(":"pZ","MLjava.awt.ContainerisFocusCycleRoot(java.awt.Container)V":"i8","MLjava.awt.ContainerrecursiveHideHeavyweightChildren(":"jN","MLjava.awt.ComponentremoveInputMethodListener(java.awt.event.InputMethodListener)V":"n0","Fjavax.swing.JComponentFOCUS_TRAVERSAL_KEYS_BACKWARD_SET":"g1","MLjavax.swing.JComponentgetInputMap(":"d9","Fjava.awt.ComponentminSizeSet":"qX","MLjava.awt.Containeradd(java.awt.Component)Vjava.lang.Object)V":"hK","MLjava.awt.ComponentrequestFocus(java.awt.event.FocusEvent.Cause)V":"oR","MLjavax.swing.GroupLayout.SequentialGroupaddContainerGap(":"tR","MLjava.awt.ContainerfindComponentAt(java.awt.Point)V":"iU","Ljavax.swing.TransferHandler":"eJ","Ljava.awt.event.KeyListener":"nJ","MLjava.awt.ComponentmouseMove(java.awt.Event)Vint)Vint)V":"ov","MLjava.io.FilerenameTo(java.io.File)V":"sX","MLjava.lang.StringBuilderappend(java.lang.String)V":"s7","MLjavax.swing.JComponentremoveVetoableChangeListener(java.beans.VetoableChangeListener)V":"fo","Fjavax.swing.JComponentalignmentY":"gf","Fjavax.swing.JComponentalignmentX":"gd","MLjava.awt.ContainergetDropTargetEventTarget(int)Vint)Vboolean)V":"iE","MLjava.awt.ComponentgetTraversalRoot(":"o5","MLjavax.swing.JComponentisDoubleBuffered(":"fU","Fjava.awt.Componentwidth":"qt","MLjavax.swing.JFramesetSize(int)Vint)V":"t9","MLjavax.swing.JComponentclientPropertyChanged(java.lang.Object)Vjava.lang.Object)Vjava.lang.Object)V":"e0","MLjava.awt.ComponentgetInputMethodRequests(":"n3","MLjavax.swing.JComponentpaintImmediately(java.awt.Rectangle)V":"fI","MLjava.awt.ComponenttransferFocusUpCycle(":"pa","MLjavax.swing.JComponentsetEnabled(boolean)V":"ei","MLjava.awt.ComponentmouseUp(java.awt.Event)Vint)Vint)V":"ou","MLjava.awt.ComponentlostFocus(java.awt.Event)Vjava.lang.Object)V":"oE","MLjava.awt.ComponentgetForeground(":"lo","MLjavax.swing.JComponentsetVisible(boolean)V":"eh","MLjava.awt.ContaineraddImpl(java.awt.Component)Vjava.lang.Object)Vint)V":"hM","Pex-Psun.util.logging":"jW","MLjava.awt.ComponentcheckGD(java.lang.String)V":"kR","Pex-Pjavax.swing.event":"fu","MLjava.awt.ComponentgetToolkit(":"kU","MLjava.awt.ContaineraddNotify(":"iV","MLjava.awt.ComponentremoveNotify(":"oC","Fjava.awt.ComponentcompoundShape":"rH","Ljava.awt.event.HierarchyEvent":"op","MLjavax.swing.GroupLayout.SequentialGroupaddPreferredGap(javax.swing.LayoutStyle.ComponentPlacement)V":"tZ","Ljava.awt.event.HierarchyListener":"nx","MLjava.security.NoSuchAlgorithmExceptionprintStackTrace(":"ta","MLjavax.swing.JComponentgetGraphicsInvoked(java.awt.Component)V":"cA","MLjavax.swing.JComponentisPaintingOrigin(":"fG","Pex-Psun.java2d.pipe":"jE","MLjava.awt.ComponentgetX(":"lY","MLjava.lang.Objectwait(long)V":"H","Fjavax.swing.JComponentvetoableChangeSupport":"gk","MLjava.awt.ComponentnextFocus(":"o7","MLjava.awt.ComponentgetCursor_NoClientCode(":"mz","Fjava.awt.ComponenthierarchyListenerK":"rp","Fjava.awt.ComponentautoFocusTransferOnDisposal":"rS","FUsergenderPreference":"bz","MLjava.awt.ContainerdecreaseComponentCount(java.awt.Component)V":"jA","MLjavax.swing.JComponentgetInputVerifier(":"dM","MLjava.awt.ContainerstartLWModal(":"iY","MLjavax.swing.JComponentsafelyGetGraphics(java.awt.Component)Vjava.awt.Component)V":"cz","Fjavax.swing.JComponentuiClassID":"f3","MLjava.awt.Containerinvalidate(":"h7","MLjava.awt.ComponentaddInputMethodListener(java.awt.event.InputMethodListener)V":"nY","MLjava.awt.ContainerlightweightPaint(java.awt.Graphics)V":"im","MLjava.awt.ComponentlightweightPrint(java.awt.Graphics)V":"mM","MLjava.awt.ComponentaddHierarchyListener(java.awt.event.HierarchyListener)V":"nw","MLjava.awt.ComponentcheckImage(java.awt.Image)Vint)Vint)Vjava.awt.image.ImageObserver)V":"m1","MLjava.awt.ContainerdispatchEventImpl(java.awt.AWTEvent)V":"iB","MLjava.awt.ComponentisMinimumSizeSet(":"ma","Fjava.awt.ComponentcoalescingEnabled":"rN","MLjavax.swing.JComponentprocessKeyEvent(java.awt.event.KeyEvent)V":"es","MLjava.io.FileWriterFileWriter(java.lang.String)Vboolean)V":"sI","MLjava.awt.Containerpaint(java.awt.Graphics)V":"ii","LViewProfile":"s","MLjavax.swing.JComponentdropLocationForPoint(java.awt.Point)V":"eL","MLjavax.swing.JComponentrevalidate(":"fD","MLjava.awt.ComponentgetListeners(java.lang.Class<T>)V":"n2","MLjava.awt.ComponentisDisplayable(":"k0","Fjava.awt.Componentenabled":"qF","MLjavax.swing.JComponentupdateUI(":"cO","Pex-Pjava.lang":"t","Fjava.awt.ContainermodalComp":"kn","MLjava.awt.ComponentsetSize(java.awt.Dimension)V":"lO","MLjava.awt.ComponentisCursorSet(":"mA","Fjavax.swing.JComponentisAlignmentYSet":"ge","FUserlastName":"bx","MLjava.awt.Containeradd(java.lang.String)Vjava.awt.Component)V":"hs","MLjavax.swing.JComponentputClientProperty(java.lang.Object)Vjava.lang.Object)V":"eZ","MLjava.awt.ContainergetComponentZOrder(java.awt.Component)V":"hJ","MLjavax.swing.JComponentgetNextFocusableComponent(":"dd","Fjava.awt.ComponentserialVersionUID":"rB","Ljava.io.FileNotFoundException":"sY","Ljavax.swing.Icon":"tr","MLjava.awt.ContainergetFocusTraversalPolicy(":"jf","MLjava.awt.ComponentreshapeNativePeer(int)Vint)Vint)Vint)Vint)V":"lV","MLjavax.swing.JPanelsetCursor(java.awt.Cursor)V":"ti","Fjavax.swing.JComponentIS_OPAQUE":"gE","Fjavax.swing.JComponentcomponentObtainingGraphicsFromLock":"hb","MLjava.awt.ComponentgetMousePosition(":"k8","MLjava.awt.Componentrepaint(int)Vint)Vint)Vint)V":"mI","Fjava.awt.ComponentmouseListenerK":"ri","MLjava.awt.ComponentdoSwingSerialization(":"pG","MLjava.awt.ComponentsetLocation(java.awt.Point)V":"lJ","MLjava.awt.Containerlist(java.io.PrintWriter)Vint)V":"i3","Ljava.security.MessageDigest":"s0","MLjava.awt.ComponentconstructComponentName(":"kB","MLjava.awt.ComponentmixOnHiding(boolean)V":"qc","MLUsersetUID(int)V":"bb","MLjavax.swing.JComponentfirePropertyChange(java.lang.String)Vchar)Vchar)V":"fj","MLjavax.swing.JFrameJFrame(":"tf","MLjava.io.BufferedReaderreadLine(":"sr","Ljava.io.IOException":"su","MLjava.awt.ComponentisRequestFocusAccepted(boolean)Vboolean)Vjava.awt.event.FocusEvent.Cause)V":"o1","MLUsertoString(":"bf","Ljava.awt.event.HierarchyBoundsListener":"nB","Ljavax.swing.AncestorNotifier":"fs","MLjavax.swing.JPanelJPanel(":"tc","MLjava.awt.ContainercountHierarchyMembers(":"hX","FUsergender":"bA","MLjavax.swing.JComponentgetPreferredSize(":"ds","MLjava.awt.ContainerdoLayout(":"h3","MLjava.awt.ComponentimageUpdate(java.awt.Image)Vint)Vint)Vint)Vint)Vint)V":"mP","MLUserOperationsViewProfile(User)V":"bO","Ljava.awt.Event":"iK","MLjavax.swing.JComponentgetVisibleRect(":"fg","MLjavax.swing.JComponentgetActionMap(":"ea","Fjava.awt.ContainerserialVersionUID":"kd","MLjava.awt.ComponentgetLocationOnScreen(":"lD","MLjava.awt.ComponentrequestFocus(boolean)Vjava.awt.event.FocusEvent.Cause)V":"oU","MLjava.awt.ComponentfirePropertyChange(java.lang.String)Vfloat)Vfloat)V":"pE","Ljava.awt.PopupMenu":"pg","MLjava.io.FileWriterclose(":"sN","MLjava.awt.Containerinsets(":"hq","Fjava.awt.ContainercontainerListener":"j;","MLjava.lang.ObjectgetClass(":"y","MLjavax.swing.JComponentsetFocusTraversalKeys(int)Vjava.util.Set<? extends java.awt.AWTKeyStroke>)V":"e2","Fjava.awt.ComponentmouseWheelListenerK":"rk","MLjavax.swing.JComponentisRequestFocusEnabled(":"df","MLjava.awt.ContainerpaintHeavyweightComponents(java.awt.Graphics)V":"in","MLjava.util.RandomnextInt(int)V":"si","Fjava.awt.Componentpeer":"qo","MLjavax.swing.JComponenthide(":"f2","MLjava.awt.ComponentisLightweight(":"l6","Pex-Pjavax.swing":"bQ","MLjava.awt.ComponentgetFont_NoClientCode(":"lv","Ljava.awt.event.FocusEvent.Cause":"oS","Ljava.net.URL":"tv","Fjava.awt.ComponentbufferStrategy":"qC","Fjava.awt.ContainernumOfHWComponents":"kg","MLjava.awt.ComponentgetGraphics(":"ms","Fjava.awt.ComponentcoalesceMap":"rO","MLPictureequalsPic(Picture)V":"P","MLjavax.swing.JComponentgetFlag(int)V":"fQ","MLjava.awt.ComponentareInputMethodsEnabled(":"nk","Ljava.awt.im.InputContext":"n7","short":"g","Fjava.awt.Componentforeground":"qv","Fjava.awt.ComponenttextListenerK":"rl","MLjava.awt.ComponentenableInputMethods(boolean)V":"lg","MLjava.lang.StringBuildertoString(":"s;","MLjava.awt.ContainergetInsets(":"hp","MLjava.awt.ComponentcheckTreeLock(":"kT","MLjava.awt.ComponentgetGraphicsConfiguration_NoClientCode(":"kM","MLjava.awt.ComponentremoveMouseListener(java.awt.event.MouseListener)V":"nO","Fjavax.swing.JComponentINHERITS_POPUP_MENU":"gX","Ljava.awt.event.ContainerEvent":"iA","FEventname":"N","Ljava.awt.image.ImageObserver":"ks","MLjavax.swing.JComponentaddNotify(":"fz","MLjavax.swing.JComponentsetVerifyInputWhenFocusTarget(boolean)V":"dl","Ljava.beans.PropertyChangeListener":"js","MLjava.awt.ContainergetLayout(":"h1","MLjavax.swing.JFramesetDefaultCloseOperation(int)V":"t;","MLjava.awt.ComponentdispatchEvent(java.awt.AWTEvent)V":"nf","MLjavax.swing.JComponentreadObject(java.io.ObjectInputStream)V":"fY","MLjava.awt.ComponentupdateChildGraphicsData(java.awt.GraphicsConfiguration)V":"kQ","Ljava.awt.event.MouseListener":"nN","MLjava.awt.ComponentapplyComponentOrientation(java.awt.ComponentOrientation)V":"pL","MLjava.awt.ContainerprintHeavyweightComponents(java.awt.Graphics)V":"iq","MLjava.awt.ComponentgetLocationOnScreen_NoTreeLock(":"lE","LUserOperations":"r","double":"b","MLjava.awt.ContainerfindTraversalRoot(":"i9","Fjava.awt.ComponentmouseWheelListener":"q.","MLjava.util.ArrayListadd(E)V":"sk","MLjava.lang.StringcompareToIgnoreCase(java.lang.String)V":"sl","MLjava.awt.ComponentsubtractAndApplyShape(sun.java2d.pipe.Region)V":"p;","Ljava.io.FileWriter":"sH","Fjava.awt.Componentheight":"qu","MLjava.awt.ComponentgetKeyListeners(":"nL","MLPicturePicture(int)V":"O","MLjavax.swing.JComponentpaint(java.awt.Graphics)V":"cZ","Fjava.awt.ComponentmouseListener":"q9","MLjavax.swing.JComponentprintComponent(java.awt.Graphics)V":"c5","MLjavax.swing.JComponentgetActionMap(boolean)V":"ec","MLjava.awt.ComponentcheckImage(java.awt.Image)Vjava.awt.image.ImageObserver)V":"m0","MLjava.awt.Componentupdate(java.awt.Graphics)V":"mC","MLUserOperationsAuthenticateUser(java.lang.String)Vjava.lang.String)V":"bH","MLjavax.swing.JComponentunregisterWithKeyboardManager(":"dV","MLjava.io.Fileexists(":"sE","MLjava.awt.ContainerlightweightPrint(java.awt.Graphics)V":"ip","MLjava.awt.ContainerapplyComponentOrientation(java.awt.ComponentOrientation)V":"jp","MLjava.awt.ComponentgetContainingWindow(":"pP","MLjava.lang.ExceptionprintStackTrace(":"r.","MLjava.awt.ComponenttransferFocus(boolean)V":"o8","MLjava.awt.ComponentgetFocusTraversalKeysEnabled(":"oP","MLjava.awt.ContainerisParentOf(java.awt.Component)V":"i.","Fjavax.swing.JComponentIS_REPAINTING":"gN","Ljava.io.ObjectInputStream":"fZ","Fjavax.swing.JComponentFOCUS_INPUTMAP_CREATED":"gG","MLSearchFunctionApplyUserFilter(java.lang.String)V":"U","MLjavax.swing.JComponentprintAll(java.awt.Graphics)V":"c3","Ljava.io.ObjectStreamField":"kk","MLjava.awt.ContainermixOnReshaping(":"jS","MLjavax.swing.JComponentgetPopupLocation(java.awt.event.MouseEvent)V":"eC","FUserUID":"bv","Fjava.awt.ContainerpreserveBackgroundColor":"kc","MLjava.awt.ComponentsetBounds(int)Vint)Vint)Vint)V":"lS","MLjava.lang.StringisEmpty(":"sG","MLjava.awt.ComponentgetLocation(":"lC","MLjava.awt.ComponenttransferFocus(":"o6","MLjava.awt.ContainercreateChildHierarchyEvents(int)Vlong)Vboolean)V":"h0","MLjavax.swing.JComponentgetInputMap(int)Vboolean)V":"eb","MLjava.awt.ContainerhasHeavyweightDescendants(":"hz","MLjava.awt.ComponentareBoundsValid(":"pX","MLjava.awt.ContainerfindComponentAtImpl(int)Vint)Vboolean)V":"iS","Ljava.awt.PointerInfo":"k7","Fjava.awt.ComponentprefSize":"qY","MLjava.awt.ContainerrecursiveApplyCurrentShape(int)Vint)V":"jL","MLjavax.swing.JComponentgetSize(java.awt.Dimension)V":"e7","Ljava.awt.MenuContainer":"kt","Ljava.io.BufferedReader":"sm","MLjavax.swing.JComponentgetLocation(java.awt.Point)V":"e8","MLjava.awt.ComponentcreateBufferStrategy(int)V":"m2","char":"i","Fjavax.swing.JComponentKEY_EVENTS_ENABLED":"gF","MLjavax.swing.JFrameadd(java.awt.Component)Vjava.lang.Object)V":"t5","MLjavax.swing.JComponentisLightweightComponent(java.awt.Component)V":"e4","Fjava.awt.ContainermodalAppContext":"ko","MLjavax.swing.JComponentsetDebugGraphicsOptions(int)V":"dO","MLjava.awt.ComponentsetAutoFocusTransferOnDisposal(boolean)V":"pd","MLjava.awt.ComponentisAutoFocusTransferOnDisposal(":"pe","MLjavax.swing.JComponentregisterWithKeyboardManager(javax.swing.KeyStroke)V":"dY","MLjavax.swing.JComponentgetWidth(":"e.","MLjava.awt.ContainercreateHierarchyEvents(int)Vjava.awt.Component)Vjava.awt.Container)Vlong)Vboolean)V":"hZ","MLjavax.swing.JPanelsetUI(javax.swing.plaf.PanelUI)V":"ck","MLjavax.swing.JComponentgetDefaultLocale(":"en","MLjavax.swing.JComponentremoveNotify(":"fA","MLjavax.swing.JComponentsetPaintingChild(java.awt.Component)V":"fK","MLjava.awt.ComponentremoveMouseWheelListener(java.awt.event.MouseWheelListener)V":"nW","MLUsergetPreferences(":"bl","Ljava.awt.event.MouseEvent":"ez","MLjava.awt.Componentremove(java.awt.MenuComponent)V":"ph","MLjavax.swing.JComponentcomputeVisibleRect(java.awt.Component)Vjava.awt.Rectangle)V":"fe","MLjava.awt.ComponentgetNormalShape(":"p1","MLjava.awt.Componentcontains(int)Vint)V":"m;","MLjava.awt.ContainerremoveContainerListener(java.awt.event.ContainerListener)V":"it","MLjava.awt.ComponentisFocusable(":"oG","Ljava.lang.Throwable":"r;","MLjava.awt.ContainersetLayout(java.awt.LayoutManager)V":"h2","MLjava.awt.ContainermixOnZOrderChanging(int)Vint)V":"jT","Fjava.awt.ComponentmouseMotionListener":"q;","MLjavax.swing.JComponentrequestFocus(":"dg","MLjava.awt.ComponentmouseEnter(java.awt.Event)Vint)Vint)V":"ow","Ljava.beans.VetoableChangeListener":"fn","Lsun.awt.EventQueueItem":"rM","FViewProfilejScrollPane1":"b4","Ljava.beans.PropertyChangeSupport":"rD","MLjava.awt.Componentcontains(java.awt.Point)V":"na","MLjava.awt.ComponentsetMinimumSize(java.awt.Dimension)V":"l.","MLjava.awt.ComponenttransferFocusBackward(":"o;","MLjava.awt.ContainerisRecursivelyVisibleUpToHeavyweightContainer(":"jP","Lsun.awt.ComponentFactory":"kY","MLUsergetGenderPreference(":";","MLjava.awt.ContainerclearMostRecentFocusOwnerOnHide(":"ja","MLjava.awt.ComponentmixOnValidating(":"qf","MLjava.awt.ComponentgetWidth(":"l0","MLjava.awt.ComponentprepareImage(java.awt.Image)Vjava.awt.image.ImageObserver)V":"mY","MLjava.awt.ComponentenableEvents(long)V":"n8","MLjava.awt.ContainerparamString(":"i0","MLjavax.swing.JComponentdisable(":"eV","Pex-Pjava.awt.dnd":"kI","MLjavax.swing.JPanelJPanel(java.awt.LayoutManager)V":"ce","MLjavax.swing.JLabelsetText(java.lang.String)V":"tp","MLjava.awt.ContainercheckAddToSelf(java.awt.Component)V":"hu","MLjavax.swing.JComponentsetDropLocation(javax.swing.TransferHandler.DropLocation)Vjava.lang.Object)Vboolean)V":"eN","MLjavax.swing.JComponentpaintComponent(java.awt.Graphics)V":"cV","MLjava.awt.ComponentgetLocale(":"ly","MLjava.awt.ComponentupdateSelfGraphicsData(java.awt.GraphicsConfiguration)V":"kP","MLjava.awt.ComponentisEnabledImpl(":"la","MLjavax.swing.JComponentalwaysOnTop(":"fJ","MLjavax.swing.JComponentsetComponentPopupMenu(javax.swing.JPopupMenu)V":"cL","MLjavax.swing.JComponentenable(":"eU","MLjava.awt.ComponentpostsOldMouseEvents(":"ol","MLjavax.swing.JComponentsafelyGetGraphics(java.awt.Component)V":"cw","MLjava.awt.ContainerisRemoveNotifyNeeded(java.awt.Component)Vjava.awt.Container)Vjava.awt.Container)V":"hC","MLjava.awt.ComponentgetTreeLock(":"kS","MLjava.awt.ContainergetAlignmentX(":"ig","MLjava.awt.ComponentsetPreferredSize(java.awt.Dimension)V":"l7","MLjava.awt.ComponentaddNotify(":"oB","Fjava.awt.ContainerdescendantsCount":"kb","MLjava.awt.ContainerinvalidateParent(":"h6","MLjava.awt.MenuContainerremove(java.awt.MenuComponent)V":"r5","MLjava.awt.ContainerisValidateRoot(":"h5","MLjava.awt.ComponentremoveMouseMotionListener(java.awt.event.MouseMotionListener)V":"nS","Fjava.awt.Containercomponent":"j0","MLjava.awt.ComponentprocessMouseEvent(java.awt.event.MouseEvent)V":"oi","MLjavax.swing.JComponentresetKeyboardActions(":"d5","MLjava.awt.Componentenable(boolean)V":"ld","MLViewProfileViewProfile(User)V":"bS","MLjavax.swing.JComponentgetInheritsPopupMenu(":"cK","MLjavax.swing.JComponentsetAlignmentY(float)V":"dG","MLjavax.swing.JComponentgetManagingFocusForwardTraversalKeys(":"cC","MLjava.awt.Componenthide(":"ln","Fjava.awt.ComponentappContext":"qq","MLjava.awt.ContainergetAlignmentY(":"ih","Fjava.awt.ComponentprefSizeSet":"qZ","Ljavax.swing.JFrame":"b9","MLjava.awt.Containerremove(java.awt.Component)V":"hR","Ljavax.swing.JPopupMenu":"cM","MLjava.awt.ComponenthandleEvent(java.awt.Event)V":"or","MLjava.awt.ComponentapplyCurrentShapeBelowMe(":"p.","MLjava.awt.ContainergetAccessibleAt(java.awt.Point)V":"jw","Fjava.awt.ComponentrequestFocusController":"rR","MLjavax.swing.JComponentregisterWithKeyboardManager(boolean)V":"dU","Fjavax.swing.JComponentfocusController":"he","MLjavax.swing.JComponentgetTransferHandler(":"eK","MLjavax.swing.JFramesetVisible(boolean)V":"t6","MLjavax.swing.JComponentprocessMouseEvent(java.awt.event.MouseEvent)V":"eP","MLjavax.swing.JComponentgetCreatedDoubleBuffer(":"eT","Fjava.awt.Componentlog":"qk","LEvent":"m","Ljava.awt.ImageCapabilities":"mX","Fjava.awt.ComponentadjustmentListenerK":"rc","MLjava.awt.Componentrepaint(long)V":"mH","MLjava.awt.ContainersetComponentZOrder(java.awt.Component)Vint)V":"hD","MLjava.awt.Containerlayout(":"h4","MLjava.awt.ComponentprintAll(java.awt.Graphics)V":"mL","MLjava.awt.ComponentremovePropertyChangeListener(java.beans.PropertyChangeListener)V":"ps","Fjavax.swing.JComponentIS_PRINTING":"gL","MLjava.awt.ComponentgetGraphicsConfiguration(":"kL","MLjava.awt.ContainerreparentTraverse(java.awt.peer.ContainerPeer)Vjava.awt.Container)V":"hE","Ljava.awt.event.MouseMotionListener":"nR","MLjava.awt.ComponentgetPropertyChangeListeners(java.lang.String)V":"pw","MLjava.awt.Componentlocation_NoClientCode(":"lG","FUserbio":"bB","MLjava.awt.ContainercheckGD(java.lang.String)V":"hP","Fjavax.swing.JComponentANCESTOR_USING_BUFFER":"gC","MLjava.awt.ContainerisFocusTraversalPolicyProvider(":"jk","Ljava.awt.Rectangle":"cH","MLjavax.swing.GroupLayoutcreateSequentialGroup(":"tS","MLjava.awt.ContainergetComponentCount(":"hj","MLjava.io.FileFile(java.lang.String)V":"sD","MLjava.awt.ComponentpointRelativeToComponent(java.awt.Point)V":"k5","MLjava.awt.ComponentcontainsFocus(":"lk","MLjava.awt.Componentlist(":"pl","MLjavax.swing.JScrollPaneJScrollPane(":"td","Ljavax.swing.ImageIcon":"ts","MLjava.awt.ComponentisPreferredSizeSet(":"l8","MLPlacegetName(":"S","MLjava.lang.ObjecthashCode(":"A","MLjava.awt.ContainervalidateUnconditionally(":"h9","MLjava.awt.ComponentrequestFocusInWindow(boolean)V":"oX","FPicturepictureUID":"Q","MLjavax.swing.JComponentprint(java.awt.Graphics)V":"c4","Ljava.awt.Point":"eB","MLjavax.swing.JComponentgetTopLevelAncestor(":"fq","Ljava.lang.StringBuilder":"s5","MLjava.awt.ComponentcoalesceEvents(java.awt.AWTEvent)Vjava.awt.AWTEvent)V":"ob","Fjava.awt.Componentvisible":"qE","Ljava.awt.event.InputMethodEvent":"on","MLjava.awt.ContainerremoveAll(":"hS","Fjavax.swing.JComponentNOT_OBSCURED":"f9","Ljava.awt.peer.ComponentPeer":"p5","FUserhashedPassword":"bu","MLjavax.swing.JComponentuninstallUIAndProperties(":"cS","MLjava.awt.ComponentisBackgroundSet(":"lt","MLjava.awt.ComponentsetDropTarget(java.awt.dnd.DropTarget)V":"kH","MLjava.awt.ComponentgetBackBuffer(":"m7","Fjava.awt.ComponentcontainerListenerK":"re","FUserfirstName":"bw","MLjava.awt.ContainergetMouseEventTarget(int)Vint)Vboolean)V":"iD","MLjava.awt.ComponentnumListening(long)V":"nD","MLjava.awt.ComponentgetAccessibleIndexInParent(":"pT","Ljavax.swing.JToolTip":"eE","MLjava.awt.ComponentdeliverEvent(java.awt.Event)V":"ne","MLjava.util.RandomRandom(":"sh","MLjava.awt.ContainergetPreferredSize(":"ib","MLjava.awt.Componentpaint(java.awt.Graphics)V":"mB","MLjava.io.BufferedReaderclose(":"st","MLjavax.swing.JComponentgetAutoscrolls(":"eH","MLjava.awt.ContainerpreferredSize(":"ic","MLjava.awt.ComponentremoveHierarchyListener(java.awt.event.HierarchyListener)V":"ny","MLjava.awt.ComponentupdateZOrder(":"qj","MLjava.awt.ComponentsetMaximumSize(java.awt.Dimension)V":"md","Fjava.awt.ContainercontainerSerializedDataVersion":"kq","MLjava.awt.ComponentmixOnReshaping(":"qd","Ljava.util.Locale":"eo","MLjava.awt.ComponentupdateCursorImmediately(":"mx","MLjava.awt.Containervalidate(":"h8","MLjava.awt.ContainerincreaseComponentCount(java.awt.Component)V":"jz","MLUsergetUserName(":"4","Fjavax.swing.JComponentborder":"gn","Ljava.util.List":"g6","Ljava.util.ArrayList":"bq","Pex-Pjavax.accessibility":"b.","MLjava.awt.ComponentfirePropertyChange(java.lang.String)Vjava.lang.Object)Vjava.lang.Object)V":"px","MLjava.awt.ContainergetComponentAt(java.awt.Point)V":"iN","MLjavax.swing.JComponentgetMaximumSize(":"du","Ljava.awt.FocusTraversalPolicy":"je","MLjavax.swing.JComponentpaintToOffscreen(java.awt.Graphics)Vint)Vint)Vint)Vint)Vint)Vint)V":"fM","Fjavax.swing.JComponentIS_PRINTING_ALL":"gM","Fjava.awt.Componentbackground":"qw","MLUsersetPreferences(java.lang.Boolean[])V":"bj","MLjavax.swing.JComponentsetUI(javax.swing.plaf.ComponentUI)V":"cR","MLjava.awt.Containerlocate(int)Vint)V":"iM","MLjava.awt.ComponentisForegroundSet(":"lq","MLjava.awt.ComponentgetHierarchyListeners(":"nz","MLjavax.swing.JComponentgetComponentGraphics(java.awt.Graphics)V":"cU","MLjava.awt.ComponentgetPropertyChangeListeners(":"pt","MLjava.awt.ComponenteventTypeEnabled(int)V":"nm","MLjava.awt.ComponentminimumSize(":"mc","Fjava.awt.ContainerfocusTraversalPolicyProvider":"j6","Fjavax.swing.JComponentWRITE_OBJ_COUNTER_FIRST":"gO","Lsun.java2d.pipe.Region":"jF","MLjava.lang.Stringequals(java.lang.Object)V":"sx","Ljava.awt.LayoutManager":"cd","MLjava.awt.ComponentapplyCurrentShape(":"p9","MLjavax.accessibility.AccessiblegetAccessibleContext(":"r8","Ljava.lang.NumberFormatException":"sA","MLjava.awt.CursorCursor(int)V":"tj","MLjava.io.PrintWriterprintln(java.lang.String)V":"sT","MLjavax.swing.JComponentupdate(java.awt.Graphics)V":"cY","MLjava.awt.ComponentrequestFocusHelper(boolean)Vboolean)Vjava.awt.event.FocusEvent.Cause)V":"o0","Ljava.io.FileReader":"sp","MLjava.awt.ContainerupdateChildGraphicsData(java.awt.GraphicsConfiguration)V":"hN","MLjava.awt.ComponentsetFocusTraversalKeys(int)Vjava.util.Set<? extends java.awt.AWTKeyStroke>)V":"oJ","MLjava.awt.ComponentfirePropertyChange(java.lang.String)Vdouble)Vdouble)V":"pF","Fjava.awt.Componentpopups":"qI","MLjava.awt.ContainerrecursiveSubtractAndApplyShape(sun.java2d.pipe.Region)V":"jG","MLjava.awt.ComponentgetInputMethodListeners(":"n1","MLjava.awt.ContainergetComponents_NoClientCode(":"hn","Fjavax.swing.JComponentwindowInputMap":"g9","Ljava.awt.Cursor":"mw","MLjava.awt.ContaineraddPropertyChangeListener(java.lang.String)Vjava.beans.PropertyChangeListener)V":"jt","MLjava.awt.ContainernumListening(long)V":"hT","Fjava.awt.ComponenteventMask":"rt","MLjava.awt.ComponentareFocusTraversalKeysSet(int)V":"oN","MLjava.awt.ContainerdeliverEvent(java.awt.Event)V":"iJ","MLjava.awt.ComponentgetContainer(":"kG","Fjava.awt.ComponentfocusTraversalKeyPropertyNames":"qS","MLjava.awt.ContainergetComponents(":"hm","MLjava.awt.ComponentremoveHierarchyBoundsListener(java.awt.event.HierarchyBoundsListener)V":"nC","MLjava.awt.ComponentgetLocation(java.awt.Point)V":"l4","MLjava.awt.ComponentremoveKeyListener(java.awt.event.KeyListener)V":"nK","Ljava.awt.Window":"pQ","Fjava.awt.ComponentmaxSize":"q0","MLjavax.swing.JPanelparamString(":"cp","Ljava.awt.event.MouseWheelEvent":"ni","Fjava.awt.ContainerlisteningChildren":"j.","MLjavax.swing.GroupLayout.SequentialGroupaddGap(int)Vint)Vint)V":"tU","Fjava.awt.ContainerlisteningBoundsChildren":"ka","MLUsergetPassword(":"5","Fjava.awt.ContainerSEARCH_HEAVYWEIGHTS":"kf","MLjava.awt.ComponentgetFocusTraversalKeys(int)V":"oK","Fjavax.swing.JComponentfocusInputMap":"g7","Fjava.awt.ContainermixingLog":"ki","MLjava.awt.ComponentgetFocusListeners(":"nv","MLjava.awt.ComponentremovePropertyChangeListener(java.lang.String)Vjava.beans.PropertyChangeListener)V":"pv","MLjavax.swing.JComponentgetInputMap(int)V":"d8","MLUserdeactivateAccount(":"bi","MLjava.awt.ComponentsetFocusable(boolean)V":"oH","MLjava.util.ScannerScanner(java.io.InputStream)V":"sd","MLjava.awt.ComponentaddMouseMotionListener(java.awt.event.MouseMotionListener)V":"nQ","MLjava.awt.Componentprint(java.awt.Graphics)V":"mK","Ljavax.swing.ActionMap":"d.","MLjava.awt.ContainermixOnHiding(boolean)V":"jR","Ljavax.swing.JLabel":"bV","MLjava.awt.ComponentaddKeyListener(java.awt.event.KeyListener)V":"nI","MLjava.security.MessageDigestupdate(byte[])V":"s2","MLjavax.swing.JTextAreasetRows(int)V":"tA","MLjavax.swing.JComponentgetUIClassID(":"cT","MLjava.awt.ComponentisSameOrAncestorOf(java.awt.Component)Vboolean)V":"k9","MLEventgetName(":"M","MLjavax.swing.JComponentgetMinimumSize(":"dw","MLjavax.swing.JComponentgrabFocus(":"dk","Fjavax.swing.JComponentlistenerList":"gh","FUserusername":"bt","MLjava.awt.ComponentmouseDrag(java.awt.Event)Vint)Vint)V":"ot","MLjava.lang.ObjectnotifyAll(":"F","MLjava.awt.ComponentsetVisible(boolean)V":"lh","MLjavax.swing.JComponentregisterNextFocusableComponent(":"c.","Fjava.awt.ComponentcomponentListener":"q4","Ljava.awt.Font":"dp","Fjava.awt.image.ImageObserverHEIGHT":"rX","LEditBio":"l","Fjava.awt.ComponentmixingLog":"qn","Fjava.awt.ComponentwindowFocusListenerK":"rs","Ljavax.swing.plaf.ComponentUI":"cQ","MLjava.awt.ComponentgetLocationOnWindow(":"p0","Ljava.io.InputStream":"se","Lsun.awt.RequestFocusController":"hg","MLjava.awt.ComponenthasFocus(":"pb","MLjavax.swing.JComponentsetPreferredSize(java.awt.Dimension)V":"dq","Fjava.awt.image.ImageObserverFRAMEBITS":"r0","MLjava.awt.ComponentclearMostRecentFocusOwnerOnHide(":"ll","MLjava.awt.ComponentfindUnderMouseInWindow(java.awt.PointerInfo)V":"k6","MLjavax.swing.JComponentisOptimizedDrawingEnabled(":"fF","Fjava.awt.ComponenteventCache":"rL","MLjava.io.FileWriterFileWriter(java.io.File)V":"sR","MLjavax.swing.JComponentisOpaque(":"fb","MLjava.awt.ComponentsetMixingCutoutShape(java.awt.Shape)V":"qh","MLjava.lang.Objectequals(java.lang.Object)V":"B","MLjava.awt.ComponentsetForeground(java.awt.Color)V":"lp","Ljava.awt.AWTEvent":"ix","MLjava.awt.ComponentsetBoundsOp(int)V":"kz","MLjava.awt.ContainerreadObject(java.io.ObjectInputStream)V":"jv","MLjava.awt.Containerremove(int)V":"hQ","MLjava.awt.ContainerpostProcessKeyEvent(java.awt.event.KeyEvent)V":"jn","Fjava.awt.Componentlocale":"qA","MLjava.awt.ContainerrecursiveSubtractAndApplyShape(sun.java2d.pipe.Region)Vint)Vint)V":"jI","MLjavax.swing.JFramesetTitle(java.lang.String)V":"t8","MLjava.awt.ComponentlightweightPaint(java.awt.Graphics)V":"mE","MLjava.awt.ContainerhasLightweightDescendants(":"hA","MLjava.awt.ComponentclearCurrentFocusCycleRootOnHide(":"lm","MLjava.awt.ContaineraddDelicately(java.awt.Component)Vjava.awt.Container)Vint)V":"hI","MLjava.awt.ComponentupdateGraphicsData(java.awt.GraphicsConfiguration)V":"kO","MLjavax.swing.GroupLayoutcreateParallelGroup(javax.swing.GroupLayout.Alignment)V":"tM","Pex-Pjava.awt.event":"dS","MLjavax.swing.JComponentsetRequestFocusEnabled(boolean)V":"de","MLjava.awt.ComponentgetComponentFactory(":"kX","MLjava.awt.ComponentaddMouseWheelListener(java.awt.event.MouseWheelListener)V":"nU","MLjavax.swing.JComponentrequestDefaultFocus(":"eg","MLjava.lang.ExceptionException(java.lang.String)V":"sj","Ljava.util.Scanner":"sc","MLUsersetGender(int)V":"8","MLjavax.swing.JComponentgetAncestorListeners(":"fx","MLjava.io.FileWriterappend(java.lang.CharSequence)V":"sK","MLjava.awt.ContainergetMouseEventTargetImpl(int)Vint)Vboolean)Vjava.awt.Container.EventTargetFilter)Vboolean)Vboolean)V":"iH","MLUserUser(java.lang.String)Vjava.lang.String)V":"Z","MLjava.awt.ComponentisVisible(":"k1","MLjava.awt.ComponentpreferredSize(":"l;","MLjava.awt.ComponentgetObjectLock(":"ku","MLjava.awt.ComponentmixOnShowing(":"qb","Ljava.io.Writer":"sL","MLjava.awt.ContainerisSameOrAncestorOf(java.awt.Component)Vboolean)V":"iP","MLjava.awt.MenuContainergetFont(":"r4","Fjava.awt.Componentfocusable":"qM","MLjava.awt.ContainerfindComponentAt(int)Vint)V":"iQ","MLjava.awt.Componentrepaint(long)Vint)Vint)Vint)Vint)V":"mJ","Fjava.awt.ComponentFOCUS_TRAVERSABLE_UNKNOWN":"qN","MLjavax.swing.JComponentgetGraphics(":"dN","MLjava.awt.ContainerminimumSize(":"ie","MLjava.awt.ComponentsetGraphicsConfiguration(java.awt.GraphicsConfiguration)V":"kN","MLjava.awt.Containeradd(java.awt.Component)Vint)V":"ht","MLjavax.swing.JTextAreaJTextArea(":"te","Fjava.awt.ComponentisInc":"ru","MLjava.awt.ComponentdispatchEventImpl(java.awt.AWTEvent)V":"ng","Fjavax.swing.JComponentverifyInputWhenFocusTarget":"gq","MLjava.awt.ComponentcalculateCurrentShape(":"p8","Ljava.util.concurrent.atomic.AtomicBoolean":"g4","MLjavax.swing.JComponentgetHeight(":"fa","MLjava.awt.Componentlist(java.io.PrintWriter)V":"po","MLjavax.swing.JLabelsetForeground(java.awt.Color)V":"tm","MLjava.awt.ContainergetOpaqueShape(":"jD","MLjava.awt.Componentshow(":"li","MLjava.awt.Componentlist(java.io.PrintStream)V":"pm","MLjava.awt.ComponentfirePropertyChange(java.lang.String)Vbyte)Vbyte)V":"pA","MLjavax.swing.JScrollPanesetViewportView(java.awt.Component)V":"tE","MLjava.awt.Containerlist(java.io.PrintStream)Vint)V":"i1","MLjava.awt.ComponentgetHierarchyBoundsListeners(":"nG","MLjava.awt.ComponentgetFocusCycleRootAncestor(":"o3","FUserinterests":"by","MLjava.awt.ContainerwriteObject(java.io.ObjectOutputStream)V":"ju","Ljava.awt.event.FocusEvent":"og","Ljava.awt.FontMetrics":"do","Ljavax.swing.ComponentInputMap":"dX","MLjava.awt.Componentresize(java.awt.Dimension)V":"lP","Ljava.util.Map":"rP","MLjavax.swing.JLabelsetFont(java.awt.Font)V":"tn","MLUserOperationsDoesExist(":"bP","MLEventEvent(java.lang.String)V":"L","MLUsergetMatches(":"bo","Pex-Pjava.io":"cn","MLjava.awt.ComponentisNonOpaqueForMixing(":"p7","MLjava.awt.ComponentautoProcessMouseWheel(java.awt.event.MouseWheelEvent)V":"nh","Fjavax.swing.JComponentmanagingFocusForwardTraversalKeys":"f7","MLjavax.swing.JComponentgetClientProperty(java.lang.Object)V":"eY","MLjavax.swing.JComponentcomponentInputMapChanged(javax.swing.ComponentInputMap)V":"dW","Fjavax.swing.JComponentinputVerifier":"gp","MLjava.awt.ComponentisFocusCycleRoot(java.awt.Container)V":"o4","Pex-Pjava.security":"kw","MLjava.awt.ComponentgetToolkitImpl(":"kW","Ljava.lang.Exception":"r9","MLjava.lang.StringindexOf(java.lang.String)V":"ss","MLjava.awt.ContainerstopLWModal(":"iZ","MLUserdeleteProfile(":"bm","Ljavax.swing.JComponent":"b;","MLjavax.swing.JComponentsetAutoscrolls(boolean)V":"eG","MLjava.awt.ContainermixOnShowing(":"jQ","MLjava.awt.ComponentaddPropertyChangeListener(java.beans.PropertyChangeListener)V":"pr","Fjava.awt.ComponentinputMethodListenerK":"ro","MLjava.awt.Componentadd(java.awt.PopupMenu)V":"pf","MLUseraddMatch(User)V":"bn","MLjava.awt.ContaineraddPropertyChangeListener(java.beans.PropertyChangeListener)V":"jr","MLjava.awt.ComponentprocessFocusEvent(java.awt.event.FocusEvent)V":"of","MLjavax.swing.JComponentfirePropertyChange(java.lang.String)Vboolean)Vboolean)V":"fh","Fjavax.swing.JComponentIS_PAINTING_TILE":"gD","Ljavax.swing.GroupLayout.SequentialGroup":"tO","Ljava.awt.Toolkit":"kV","MLjavax.swing.JComponentunregisterWithKeyboardManager(javax.swing.KeyStroke)V":"dZ","Fjava.awt.Componentname":"qK","MLjava.awt.ComponentisFocusOwner(":"pc","MLjava.awt.ContainergetComponent(int)V":"hl","MLjava.awt.ContaineradjustDescendants(int)V":"hV","MLjava.awt.ContainercontainsFocus(":"i;","Pex-Pjavax.swing.plaf":"ci","MLjava.awt.ComponentrequestFocusInWindow(":"oV","MLjava.awt.ComponentcreateImage(java.awt.image.ImageProducer)V":"mR","MLjavax.swing.JComponentgetFontMetrics(java.awt.Font)V":"dn","Ljava.io.Serializable":"cu","MLjavax.swing.GroupLayoutsetVerticalGroup(javax.swing.GroupLayout.Group)V":"tX","MLjava.awt.ContaineradjustDescendantsOnParent(int)V":"hW","Ljava.awt.peer.ContainerPeer":"hG","MLjavax.swing.JComponentderegisterNextFocusableComponent(":"db","MLjava.awt.ComponentprintHeavyweightComponents(java.awt.Graphics)V":"mN","Fjava.awt.ComponentmaxSizeSet":"q1","Ljava.awt.BorderLayout":"t3","Fjava.awt.ComponentchangeSupport":"rC","MLjava.awt.ComponentgetParent_NoClientCode(":"kF","MLjava.awt.ComponentgetRecursivelyVisibleBounds(":"k4","MLjavax.swing.JFramesetLayout(java.awt.LayoutManager)V":"t2","Ljava.security.NoSuchAlgorithmException":"s.","Fjavax.swing.JComponentINPUT_VERIFIER_SOURCE_KEY":"gb","MLjava.awt.ComponentaddFocusListener(java.awt.event.FocusListener)V":"ns","MLjavax.swing.JComponentprocessKeyBindings(java.awt.event.KeyEvent)Vboolean)V":"eu","Ljava.security.AccessControlContext":"kx","MLUsermatchUser(User)V":"br","Ljava.awt.im.InputMethodRequests":"n5","MLjavax.swing.JComponentgetClientProperties(":"eW","Pex-Pjava.awt.image":"kr","Ljava.lang.Thread":"j8","MLjava.awt.Componentlist(java.io.PrintWriter)Vint)V":"pp","Fjava.awt.image.ImageObserverSOMEBITS":"rZ","Ljava.awt.event.KeyEvent":"er","Ljavax.swing.GroupLayout.ParallelGroup":"tK","MLjavax.swing.JComponentpaintForceDoubleBuffered(java.awt.Graphics)V":"c0","MLjava.awt.ComponentprocessHierarchyEvent(java.awt.event.HierarchyEvent)V":"oo","Fjava.awt.ComponentignoreRepaint":"qD","MLjavax.swing.JPanelupdateUI(":"cg","MLjavax.swing.JComponentpaintImmediately(int)Vint)Vint)Vint)V":"fH","Ljava.lang.Integer":"sy","MLjava.awt.ContainergetMouseEventTarget(int)Vint)Vboolean)Vjava.awt.Container.EventTargetFilter)Vboolean)V":"iF","Fjava.awt.ComponenthierarchyListener":"q6","MLjava.awt.FontFont(java.lang.String)Vint)Vint)V":"to","MLjavax.swing.JComponentcreateToolTip(":"eD","MLjava.awt.ContainergetListeners(java.lang.Class<T>)V":"iv","Ljavax.accessibility.AccessibleStateSet":"pV","MLjava.awt.ComponentaddMouseListener(java.awt.event.MouseListener)V":"nM","MLjavax.swing.JComponentgetDebugGraphicsOptions(":"dP","Ljava.util.Vector":"qJ","MLjava.awt.ComponentgetInputContext(":"n6","MLjava.awt.DimensionDimension(int)Vint)V":"tl","MLUsercompareTo(E)V":"bc","Fjava.awt.ComponenthierarchyBoundsListener":"q7","MLjava.awt.ComponentkeyDown(java.awt.Event)Vint)V":"oy","Ljava.io.File":"sC","MLjavax.swing.JComponentrequestFocus(boolean)V":"dh","MLjavax.swing.JComponentgetListeners(java.lang.Class<T>)V":"fy","MLjava.awt.ContainerprocessContainerEvent(java.awt.event.ContainerEvent)V":"iz","MLUsergetGenderPreferenceString(":"9","MLjava.awt.ComponentgetMouseWheelListeners(":"nX","MLjavax.swing.JComponentgetToolTipLocation(java.awt.event.MouseEvent)V":"eA","MLjava.awt.ComponentkeyUp(java.awt.Event)Vint)V":"oz","Fjava.awt.ComponentfocusTraversalKeysEnabled":"qT","Fjava.awt.ComponentfocusListener":"q5","MLjava.awt.MenuContainerpostEvent(java.awt.Event)V":"r6","MLjava.lang.StringBuilderStringBuilder(":"s6","MLjava.awt.ComponentgetFontMetrics(java.awt.Font)V":"mu","long":"h","MLjava.awt.Componentlist(java.io.PrintStream)Vint)V":"pn","MLjava.lang.ComparablecompareTo(T)V":"bF","MLjava.awt.ContainerdispatchEventToSelf(java.awt.AWTEvent)V":"iC","LPlace":"o","MLjavax.swing.JComponentsetMaximumSize(java.awt.Dimension)V":"dt","Ljava.lang.Boolean":"bk","MLjava.awt.ComponentsetName(java.lang.String)V":"kD","Ljavax.swing.text.JTextComponent":"tC","Fjava.awt.ContainereventLog":"jY","MLjava.awt.ComponentprocessInputMethodEvent(java.awt.event.InputMethodEvent)V":"om","Fjavax.swing.JComponentclientProperties":"gj","MLjava.awt.ComponentisDoubleBuffered(":"lf","MLjava.awt.ContainereventEnabled(java.awt.AWTEvent)V":"iw","MLjava.io.FilecreateNewFile(":"sF","MLjavax.swing.JComponentgetInsets(java.awt.Insets)V":"dE","MLjava.awt.Componentreshape(int)Vint)Vint)Vint)V":"lT","LUser":"q","Ljava.awt.Container":"ct","MLjava.awt.ContainersetFocusCycleRoot(boolean)V":"jh","Fjava.awt.ComponentBOTTOM_ALIGNMENT":"ry","MLjavax.swing.JComponentgetUI(":"cP","Fjava.awt.ComponentmixingCutoutRegion":"rI","MLjavax.swing.JComponentshouldDebugGraphics(":"dQ","MLjava.awt.ComponentgetNativeContainer(":"pq","MLjava.lang.Objectnotify(":"E","Fjavax.swing.JComponentisAlignmentXSet":"gc","MLjava.awt.ContainerprocessEvent(java.awt.AWTEvent)V":"iy","Fjavax.swing.JComponentdefaultLocale":"g.","MLjava.awt.ComponentgetComponentAt(int)Vint)V":"nb","Fjava.awt.ComponentpeerFont":"qy","MLjavax.swing.JComponentsetInheritsPopupMenu(boolean)V":"cJ","MLUsersetGenderPreference(int)V":".","Ljava.awt.Color":"ek","MLjavax.swing.GroupLayout.SequentialGroupaddContainerGap(int)Vint)V":"tP","Fjava.awt.ContainerisJavaAwtSmartInvalidate":"kl","MLjava.awt.ComponentfirePropertyChange(java.lang.String)Vchar)Vchar)V":"pB","MLjavax.swing.JComponentrequestFocusInWindow(boolean)V":"dj","MLjavax.swing.JComponentrecycleRectangle(java.awt.Rectangle)V":"cI","MLjava.awt.ContainerclearCurrentFocusCycleRootOnHide(":"jb","Fjavax.swing.JComponentrevalidateRunnableScheduled":"g2","Fjavax.swing.JComponentactionMap":"g;","MLjava.awt.Componentvalidate(":"mm","MLjava.awt.ComponentcanBeFocusOwner(":"pM","Fjava.awt.ContainerdescendUnconditionallyWhenValidating":"km","Fjava.awt.ComponentcomponentListenerK":"rd","MLjava.awt.ComponentgetComponentOrientation(":"pK","MLjavax.swing.JComponentsetBorder(javax.swing.border.Border)V":"dy","Fjava.awt.ContainernumOfLWComponents":"kh","Fjava.awt.ComponentLOCK":"qU","MLjavax.swing.JComponentgetWriteObjCounter(javax.swing.JComponent)V":"fS","Ljava.awt.Shape":"qi","MLjava.awt.ComponentgetPreferredSize(":"l9","MLjava.awt.ComponentgetBounds(java.awt.Rectangle)V":"l2","Ljava.awt.Component.BaselineResizeBehavior":"ef","MLjava.awt.Componentinside(int)Vint)V":"m.","Fjava.awt.ComponentincRate":"rv","MLjava.awt.ComponentrevalidateSynchronously(":"mr","MLjava.awt.image.ImageObserverimageUpdate(java.awt.Image)Vint)Vint)Vint)Vint)Vint)V":"rV","MLjavax.swing.JComponentgetToolTipText(java.awt.event.MouseEvent)V":"ey","MLjava.awt.ContainergetMousePosition(boolean)V":"iO","MLUserOperationsCreateNewUser(User<E>)V":"bI","MLjava.awt.ComponentprocessMouseWheelEvent(java.awt.event.MouseWheelEvent)V":"ok","MLjava.awt.Componentlocate(int)Vint)V":"nc","MLjavax.swing.JComponentadjustPaintFlags(":"c2","Ljava.util.Set":"cD","MLjavax.swing.JComponentsetFont(java.awt.Font)V":"em","Fjava.awt.image.ImageObserverWIDTH":"rW","FUserstatus":"bC","MLjava.awt.ComponentrequestFocus(boolean)V":"oT","MLjava.awt.ComponentcreateImage(int)Vint)V":"mT","MLjavax.swing.JComponentrectangleIsObscured(int)Vint)Vint)Vint)V":"fd","MLjava.awt.ContainersetFont(java.awt.Font)V":"ia","MLjava.awt.ComponentgetBounds(":"lQ","MLjava.awt.ComponentdisableEvents(long)V":"n9","Ljava.awt.Component":"cy","Fjava.awt.ComponentwindowStateListenerK":"rr","Fjavax.swing.JComponentAUTOSCROLLS_SET":"gZ","Fjava.awt.image.ImageObserverPROPERTIES":"rY","MLjava.lang.Stringsplit(java.lang.String)V":"sw","MLUserOperationsRemoveUser(int)V":"bJ","MLjava.awt.ComponentgetDropTarget(":"kK","Ljavax.swing.JScrollPane":"b5","MLjavax.swing.JComponentprocessKeyBinding(javax.swing.KeyStroke)Vjava.awt.event.KeyEvent)Vint)Vboolean)V":"et","MLjava.awt.ComponentwriteObject(java.io.ObjectOutputStream)V":"pH","MLUsergetUID(":"ba","Fjava.awt.Componentacc":"qV","Lsun.awt.AppContext":"kp","Fjava.awt.ComponentfocusLog":"qm","FUserpreferences":"bD","Ljava.awt.Container.EventTargetFilter":"iG","MLjava.awt.ComponentcreateVolatileImage(int)Vint)Vjava.awt.ImageCapabilities)V":"mW","MLjavax.swing.JComponentisPaintingTile(":"c8","MLjavax.swing.JComponentsetDoubleBuffered(boolean)V":"fT","MLjava.awt.ComponentisFocusTraversableOverridden(":"oI","MLjava.awt.ComponentrequestFocusInWindow(boolean)Vjava.awt.event.FocusEvent.Cause)V":"oY","MLjava.awt.ComponentgetAccessibleStateSet(":"pU","MLjava.io.PrintWriterPrintWriter(java.io.Writer)V":"sQ","MLUsersetFirstName(java.lang.String)V":"0","Fjava.awt.ComponentkeyListenerK":"rh","MLjava.awt.ComponentpaintAll(java.awt.Graphics)V":"mD","MLjava.awt.ComponentparamString(":"pj","Fjavax.swing.JComponentREQUEST_FOCUS_DISABLED":"gW","MLjava.awt.ContainerisFocusCycleRoot(":"ji","MLjavax.swing.JComponentsetCreatedDoubleBuffer(boolean)V":"eS","Ljava.awt.MenuComponent":"pi","MLjava.awt.Componentshow(boolean)V":"lj","MLjava.awt.ComponentfirePropertyChange(java.lang.String)Vboolean)Vboolean)V":"py","MLjavax.swing.JComponentsetMinimumSize(java.awt.Dimension)V":"dv","MLjava.awt.ComponenttoString(":"pk","Fjava.awt.ComponentnewEventsOnly":"q3","Ljavax.swing.JTextArea":"b7","FViewProfilejLabel8":"b1","Fjava.awt.ContainerprintingThreads":"j7","FViewProfilejLabel9":"b2","FViewProfilejLabel4":"bX","FViewProfilejLabel5":"bY","FViewProfilejLabel6":"bZ","MLCreateNewUserexecute(":"v","FViewProfilejLabel7":"b0","FViewProfilejLabel1":"bU","MLjava.awt.ComponentgetParent(":"kE","FViewProfilejLabel2":"bW","MLUsergetGenderString(":"6","MLjava.awt.Containerupdate(java.awt.Graphics)V":"ij","MLjava.io.Filedelete(":"sW","Ljava.lang.String":"x","MLjava.awt.ContainerrecursiveApplyCurrentShape(int)V":"jK","Pex-Pjava.net":"tu","Fjavax.swing.JComponentIS_DOUBLE_BUFFERED":"gB","MLjavax.swing.JComponentgetVerifyInputWhenFocusTarget(":"dm","MLjavax.swing.JComponentprintBorder(java.awt.Graphics)V":"c7","MLjavax.swing.JComponentsetDefaultLocale(java.util.Locale)V":"ep","MLjava.awt.ComponentisInstanceOf(java.lang.Object)Vjava.lang.String)V":"pW","Fjavax.swing.JComponentDEBUG_GRAPHICS_LOADED":"ga","MLjava.awt.Componentinvalidate(":"mn","MLjavax.swing.JComponentrequestFocusInWindow(":"di","MLjava.awt.ContainerrecursiveApplyCurrentShape(":"jJ","Fjava.awt.ComponentdropTarget":"qH","MLjava.awt.ComponentsetEnabled(boolean)V":"lb","MLjavax.swing.JComponentprintChildren(java.awt.Graphics)V":"c6","MLjavax.swing.JTextAreasetForeground(java.awt.Color)V":"tz","MLjava.awt.Componentlocation(":"lF","MLjava.lang.Objectclone(":"C","MLjava.awt.ContainervalidateTree(":"h;","MLjava.awt.ComponentrequestFocusInWindow(java.awt.event.FocusEvent.Cause)V":"oW","MLjava.awt.ComponentsetRequestFocusController(sun.awt.RequestFocusController)V":"o2","Fjava.awt.ComponentinputMethodListener":"ra","MLjava.awt.ComponentfirePropertyChange(java.lang.String)Vlong)Vlong)V":"pD","MLjava.awt.ContainercheckNotAWindow(java.awt.Component)V":"hv","Fjavax.swing.JComponentflags":"go","Fjava.awt.ComponentgraphicsConfig":"qB","MLjava.awt.ComponentgetMinimumSize(":"mb","MLjavax.swing.JComponentaddAncestorListener(javax.swing.event.AncestorListener)V":"ft","MLjava.io.PrintWriterflush(":"sU","Ljava.awt.image.BufferStrategy":"m6","Fjava.awt.ComponentcoalesceEventsParams":"rQ","Ljava.awt.Insets":"dD","Fjava.awt.ComponentitemListenerK":"rg","Fjava.awt.ContainerINCLUDE_SELF":"ke","MLjava.awt.ComponentmixOnZOrderChanging(int)Vint)V":"qe","MLjava.awt.ComponentgetAccessControlContext(":"kv","MLjavax.swing.JComponentsetFlag(int)Vboolean)V":"fP","MLjavax.swing.JComponentregisterKeyboardAction(java.awt.event.ActionListener)Vjavax.swing.KeyStroke)Vint)V":"d0","Fjava.awt.Containerdispatcher":"j2","MLjavax.swing.JComponent_paintImmediately(int)Vint)Vint)Vint)V":"fL","MLjava.awt.ComponentrequestFocusHelper(boolean)Vboolean)V":"oZ","MLjava.awt.ComponentcreateBufferStrategy(int)Vjava.awt.BufferCapabilities)V":"m3","MLjavax.swing.JComponentgetBorder(":"dB","Fjava.awt.ComponenthierarchyBoundsListenerK":"rq","Ljava.awt.AWTKeyStroke":"e3","MLjavax.swing.JComponentgetManagingFocusBackwardTraversalKeys(":"cF","Fjava.awt.ComponenteventLog":"ql","MLjava.awt.ComponentsetSize(int)Vint)V":"lM","MLjava.awt.ContainerproxyEnableEvents(long)V":"iI","MLjava.awt.ComponentgetBaseline(int)Vint)V":"mi","MLjava.awt.ComponentaddComponentListener(java.awt.event.ComponentListener)V":"no","MLjavax.swing.JPanelsetPreferredSize(java.awt.Dimension)V":"tk","Fjava.awt.ComponentFOCUS_TRAVERSABLE_SET":"qP","MLjava.awt.ContainercheckAdding(java.awt.Component)Vint)V":"hw","MLjavax.swing.JComponentregisterNextFocusableComponent(java.awt.Component)V":"da","MLjava.awt.ComponentrepaintParentIfNeeded(int)Vint)Vint)Vint)V":"lU","MLjavax.swing.JComponentsetBackground(java.awt.Color)V":"el","Fjavax.swing.JComponentpaintingChild":"gr","MLjavax.swing.JComponentisPaintingForPrint(":"c9","float":"d","MLjava.awt.ComponenttransferFocusBackward(boolean)V":"o.","MLjava.awt.ComponentgetBaselineResizeBehavior(":"mj","MLjavax.swing.JComponentprocessKeyBindingsForAllComponents(java.awt.event.KeyEvent)Vjava.awt.Container)Vboolean)V":"ev","MLjavax.swing.GroupLayoutGroupLayout(java.awt.Container)V":"tG","MLjavax.swing.JComponentcontains(int)Vint)V":"dx","MLjavax.swing.JComponentgetAncestorNotifier(":"fr","Ljavax.swing.GroupLayout.Alignment":"tN","MLjava.awt.ContainerpreProcessKeyEvent(java.awt.event.KeyEvent)V":"jm","Fjavax.swing.JPaneluiClassID":"cs","MLjava.lang.IntegertoString(int)V":"sO","MLjava.awt.ComponentremoveComponentListener(java.awt.event.ComponentListener)V":"nq","MLjava.awt.ComponentisFontSet(":"lx","MLjavax.swing.JComponentisManagingFocus(":"c;","Pex-Pjava.awt.peer":"hF","Fjava.awt.Componentfont":"qx","Ljavax.swing.GroupLayout.Group":"tJ","Fjava.awt.ComponentisPacked":"rF","MLjavax.swing.JComponentsetInputMap(int)Vjavax.swing.InputMap)V":"d6","MLjavax.swing.JComponentgetActionForKeyStroke(javax.swing.KeyStroke)V":"d4","Fjavax.swing.JComponentcomponentObtainingGraphicsFrom":"ha","MLUsergetGender(":"7","MLjavax.swing.JPanelJPanel(boolean)V":"cf","MLjava.lang.ClassgetResource(java.lang.String)V":"tw","MLEditBiomain(java.lang.String[])V":"K","Fjavax.swing.JComponentWRITE_OBJ_COUNTER_LAST":"gV","MLjavax.swing.JPanelsetBackground(java.awt.Color)V":"tg","MLjavax.swing.JPanelwriteObject(java.io.ObjectOutputStream)V":"cm","Fjavax.swing.JComponentWHEN_IN_FOCUSED_WINDOW_BINDINGS":"gx","MLjavax.swing.JComponentaddVetoableChangeListener(java.beans.VetoableChangeListener)V":"fl","MLjava.awt.ContainersetFocusTraversalKeys(int)Vjava.util.Set<? extends java.awt.AWTKeyStroke>)V":"i5","MLjava.io.FilegetAbsolutePath(":"sP","MLjavax.swing.JComponentgetAlignmentX(":"dH","MLjavax.swing.JComponentrepaint(long)Vint)Vint)Vint)Vint)V":"fB","Ljava.awt.LightweightDispatcher":"j3","MLjavax.swing.JComponentpaintChildren(java.awt.Graphics)V":"cW","MLjavax.swing.JComponentvalidateAlignment(float)V":"dJ","MLjavax.swing.JFramesetLocationRelativeTo(java.awt.Component)V":"ua","MLjava.lang.ObjecttoString(":"D","Ljavax.swing.event.AncestorListener":"fv","Ljava.awt.dnd.DropTarget":"kJ","MLjava.awt.ComponentgetMaximumSize(":"mf","MLjavax.swing.JComponentcomputeVisibleRect(java.awt.Rectangle)V":"ff","MLjava.awt.ContainerinvalidateTree(":"h.","MLjava.awt.ComponentcreateVolatileImage(int)Vint)V":"mU","MLjava.awt.ComponentgetGraphics_NoClientCode(":"mt","Ljavax.swing.ArrayTable":"eX","Ljava.awt.image.VolatileImage":"mV","MLjava.awt.ComponentgetMouseListeners(":"nP","MLjava.awt.Componentresize(int)Vint)V":"lN","MLjava.security.MessageDigestgetInstance(java.lang.String)V":"s1","MLjavax.swing.JComponentsetOpaque(boolean)V":"fc","MLjava.awt.ComponentsetBackground(java.awt.Color)V":"ls","MLjava.awt.ComponentsetFocusTraversalKeysEnabled(boolean)V":"oO","MLjavax.swing.JComponentgetAlignmentY(":"dF","Pex-Pjava.beans":"fm","Ljava.util.Hashtable":"f5","MLjavax.swing.JComponentregisterKeyboardAction(java.awt.event.ActionListener)Vjava.lang.String)Vjavax.swing.KeyStroke)Vint)V":"dR","Ljava.awt.ComponentOrientation":"jq","MLjava.awt.ComponentgetOpaqueShape(":"p2","MLjava.awt.ComponentisEnabled(":"k.","Ljava.awt.image.ImageProducer":"mS","MLjava.awt.ComponentgetFont(":"lu","Pex-Pjavax.swing.text":"tB","MLjavax.swing.JTextAreasetColumns(int)V":"ty","MLjavax.swing.JComponentisPainting(":"c1","int":"c","Fjava.awt.ContainerserialPersistentFields":"kj","Fjava.awt.ComponentTOP_ALIGNMENT":"rw","Fjava.awt.ComponentobjectLock":"rE","boolean":"e","FSearchFunctionlistUserFilters":"W","Fjava.awt.ContainerfocusCycleRoot":"j5","MLjavax.swing.GroupLayout.ParallelGroupaddComponent(java.awt.Component)Vint)Vint)Vint)V":"tT","FViewProfileframe":"b8","Fjava.awt.ComponentkeyListener":"q8","MLjava.awt.ComponentgetIgnoreRepaint(":"m9","MLjava.awt.ComponentgetHWPeerAboveMe(":"p4","MLjava.awt.ComponentisValid(":"kZ","MLjava.awt.ComponentgetBufferStrategy(":"m5","Ljavax.swing.WindowConstants":"t.","MLjava.awt.ContainergetChildAt(java.awt.Component)Vint)Vint)Vboolean)V":"iT","Ljava.awt.event.FocusListener":"nt","MLjava.lang.NumberFormatExceptionprintStackTrace(":"sB"}}